recordpack/__init__.py
recordpack/be.py
recordpack/encoder.py
recordpack/exceptions.py
recordpack/helpers.py
recordpack/provider.py
recordpack/proxy.py
recordpack/recordpack.py
recordpack/results.py
recordpack/signals.py
recordpack/typecast.py
recordpack/demo/__init__.py
recordpack/demo/actions.py
recordpack/demo/app_meta.py
recordpack/demo/column_filter.py
recordpack/demo/controller.py
recordpack/demo/models.py
recordpack/demo/proxy.py
recordpack/demo/ui.py
m3_recordpack-0.1.0.72.dist-info/LICENSE
m3_recordpack-0.1.0.72.dist-info/METADATA
m3_recordpack-0.1.0.72.dist-info/WHEEL
m3_recordpack-0.1.0.72.dist-info/top_level.txt
m3_recordpack-0.1.0.72.dist-info/RECORD
