Metadata-Version: 2.1
Name: m3-recordpack
Version: 0.1.0.72
Summary: Пак общего назначения, для формирования и управления журнальными окнами и окнами справочников
Author: Bars Group
Author-email: bars@bars-open.ru
Maintainer: Torsunov Andrey
Maintainer-email: torsunov@bars-open.ru
License: MIT
Keywords: django m3
Classifier: Intended Audience :: Developers
Classifier: Environment :: Web Environment
Classifier: Natural Language :: Russian
Classifier: Natural Language :: English
Classifier: Operating System :: OS Independent
Classifier: Programming Language :: Python
Classifier: License :: OSI Approved :: MIT License
Classifier: Development Status :: 5 - Production/Stable
License-File: LICENSE
Requires-Dist: m3-core
Requires-Dist: m3-ui
Requires-Dist: django
